applications_superstaq/__init__.py
applications_superstaq/_init_vars.py
applications_superstaq/_version.py
applications_superstaq/converters.py
applications_superstaq/converters_test.py
applications_superstaq/finance.py
applications_superstaq/finance_test.py
applications_superstaq/logistics.py
applications_superstaq/logistics_test.py
applications_superstaq/py.typed
applications_superstaq/qubo.py
applications_superstaq/qubo_test.py
applications_superstaq/resource_estimate.py
applications_superstaq/resource_estimate_test.py
applications_superstaq/superstaq_client.py
applications_superstaq/superstaq_client_test.py
applications_superstaq/superstaq_exceptions.py
applications_superstaq/superstaq_exceptions_test.py
applications_superstaq/user_config.py
applications_superstaq/user_config_test.py
applications_superstaq/check/__init__.py
applications_superstaq/check/all_.py
applications_superstaq/check/build_docs.py
applications_superstaq/check/check_utils.py
applications_superstaq/check/coverage_.py
applications_superstaq/check/flake8_.py
applications_superstaq/check/format_.py
applications_superstaq/check/mypy_.py
applications_superstaq/check/pylint_.py
applications_superstaq/check/pytest_.py
applications_superstaq/check/requirements.py
applications_superstaq-0.1.15.dist-info/LICENSE
applications_superstaq-0.1.15.dist-info/METADATA
applications_superstaq-0.1.15.dist-info/WHEEL
applications_superstaq-0.1.15.dist-info/top_level.txt
applications_superstaq-0.1.15.dist-info/RECORD
