Metadata-Version: 2.1
Name: applications-superstaq
Version: 0.1.15
Summary: The applications module that provides tools and access to SuperstaQ
Home-page: https://github.com/SupertechLabs/applications-superstaq
Author: Super.tech
Author-email: pranav@super.tech
License: Apache 2
Platform: UNKNOWN
Requires-Python: >=3.6.0
Requires-Dist: qubovert (>=1.2.3)
Requires-Dist: requests (>=2.26.0)
Provides-Extra: dev
Requires-Dist: black[jupyter] (~=22.3.0) ; extra == 'dev'
Requires-Dist: flake8-import-order (~=0.18.1) ; extra == 'dev'
Requires-Dist: flake8 (~=3.8.4) ; extra == 'dev'
Requires-Dist: mypy (>=0.961) ; extra == 'dev'
Requires-Dist: nbmake (~=1.3.0) ; extra == 'dev'
Requires-Dist: pylint (>=2.13.0) ; extra == 'dev'
Requires-Dist: pytest-cov (~=2.11.1) ; extra == 'dev'
Requires-Dist: pytest-socket (~=0.4.1) ; extra == 'dev'
Requires-Dist: pytest (~=6.1.2) ; extra == 'dev'
